{
  "users": {
    "6283823097750@s.whatsapp.net": {},
    "6283825463648@s.whatsapp.net": {},
    "6282260620804@s.whatsapp.net": {},
    "6289609950580@s.whatsapp.net": {},
    "43856464740486@lid": {},
    "6287747926792@s.whatsapp.net": {},
    "62895402989678@s.whatsapp.net": {},
    "6282172475374@s.whatsapp.net": {},
    "120363405362316840@newsletter": {},
    "120363422054951473@newsletter": {},
    "6285339292131@s.whatsapp.net": {},
    "6285161721605@s.whatsapp.net": {},
    "120363419397191308@newsletter": {},
    "6282338398855@s.whatsapp.net": {},
    "628988810597@s.whatsapp.net": {},
    "6289523423361@s.whatsapp.net": {},
    "120363401328391633@newsletter": {},
    "6283171177552@s.whatsapp.net": {},
    "120363423464249455@newsletter": {},
    "120363404446053939@newsletter": {},
    "120363296171556721@newsletter": {},
    "6285701410761@s.whatsapp.net": {},
    "120363421366320253@newsletter": {},
    "120363404382794093@newsletter": {},
    "6282173642873@s.whatsapp.net": {},
    "6283175439630@s.whatsapp.net": {},
    "6285177148100@s.whatsapp.net": {},
    "62895322554987@s.whatsapp.net": {},
    "120363420619530273@newsletter": {},
    "6281274920526@s.whatsapp.net": {},
    "6283867678160@s.whatsapp.net": {},
    "6282276752273@s.whatsapp.net": {},
    "6282280059457@s.whatsapp.net": {},
    "6285692533829@s.whatsapp.net": {},
    "6282168604105@s.whatsapp.net": {},
    "62895425537487@s.whatsapp.net": {},
    "6282253595771@s.whatsapp.net": {},
    "6289505357961@s.whatsapp.net": {},
    "6282338092866@s.whatsapp.net": {},
    "6283833633779@s.whatsapp.net": {},
    "6287745148443@s.whatsapp.net": {},
    "6285772046118@s.whatsapp.net": {},
    "6283845584667@s.whatsapp.net": {},
    "6283832725593@s.whatsapp.net": {},
    "6283821667880@s.whatsapp.net": {},
    "6282147128156@s.whatsapp.net": {}
  },
  "groups": {
    "120363421029463055@g.us": {
      "antilink": false,
      "antilink2": false
    },
    "120363420069902180@g.us": {
      "antilink": false,
      "antilink2": false
    },
    "120363419791233848@g.us": {
      "antilink": false,
      "antilink2": false
    },
    "120363419812625586@g.us": {
      "antilink": false,
      "antilink2": false
    },
    "120363403602227062@g.us": {
      "antilink": false,
      "antilink2": false
    },
    "120363421265430366@g.us": {
      "antilink": false,
      "antilink2": false
    }
  },
  "settings": {
    "welcome": false,
    "developer": [],
    "reseller": [],
    "bljpm": [],
    "respon": []
  }
}